vmware_exporter/__init__.py
vmware_exporter/defer.py
vmware_exporter/helpers.py
vmware_exporter/vmware_exporter.py
vmware_exporter-0.18.4.dist-info/LICENSE
vmware_exporter-0.18.4.dist-info/METADATA
vmware_exporter-0.18.4.dist-info/WHEEL
vmware_exporter-0.18.4.dist-info/entry_points.txt
vmware_exporter-0.18.4.dist-info/top_level.txt
vmware_exporter-0.18.4.dist-info/RECORD
