Metadata-Version: 2.1
Name: vmware-exporter
Version: 0.18.4
Summary: VMWare VCenter Exporter for Prometheus
Home-page: https://github.com/pryorda/vmware_exporter
Author: Daniel Pryor
License: BSD 3-Clause License
Download-URL: https://github.com/pryorda/vmware_exporter/tarball/0.18.4
Keywords: VMWare,VCenter,Prometheus
Platform: UNKNOWN
Requires-Dist: prometheus-client (==0.0.19)
Requires-Dist: pytz
Requires-Dist: pyvmomi (>=6.5)
Requires-Dist: twisted (>=14.0.2)
Requires-Dist: pyyaml (>=5.1)
Requires-Dist: service-identity
